{"type":"FeatureCollection","features":[{"type":"Feature","geometry":{"type":"Point","coordinates":[1.9373628681628452,-1.528429075910188]},"properties":{"label":"Dale of Merchants Collection","size":"1237","ratings":"7.79273","complexity":"2.2941","min_players":"2","max_players":"4","min_players_rec":"2","max_players_rec":"4","min_players_best":"2","max_players_best":"3","min_time":"20","max_time":"60","category":"1089,1002,1010","mechanic":"2664,2072,2040,2041,2004,2686,2019,2015","bayes_rating":"6.30946","id":251551,"parent":0}},{"type":"Feature","geometry":{"type":"Point","coordinates":[-4.071974279571951,-2.09673507444938]},"properties":{"label":"Dale of Merchants 2","size":"2525","ratings":"7.28889","complexity":"2.0714","min_players":"2","max_players":"4","min_players_rec":"2","max_players_rec":"4","min_players_best":"2","max_players_best":"3","min_time":"30","max_time":"30","category":"1089,1002,1010,1120","mechanic":"2664,2072,2040,2041,2004,2686,2019","bayes_rating":"6.43731","id":191597,"parent":0}},{"type":"Feature","geometry":{"type":"Point","coordinates":[-0.6660853141574705,-6.2670777700873]},"properties":{"label":"Dale of Merchants 3","size":"784","ratings":"7.65794","complexity":"2.1429","min_players":"2","max_players":"4","min_players_rec":"2","max_players_rec":"4","min_players_best":"2","max_players_best":"4","min_time":"20","max_time":"40","category":"1089,1002,1010","mechanic":"2664,2072,2040,2041,2004,2686,2019","bayes_rating":"6.06718","id":299452,"parent":0}}]}